django_admin_search/__init__.py
django_admin_search/admin.py
django_admin_search/apps.py
django_admin_search/utils.py
django_admin_search/locale/pt_BR/LC_MESSAGES/django.mo
django_admin_search/locale/pt_BR/LC_MESSAGES/django.po
django_admin_search/static/django_admin_search/css/styles.css
django_admin_search/static/django_admin_search/jquery/jquery.min.js
django_admin_search/static/django_admin_search/jquery_mask/jquery.mask.min.js
django_admin_search/static/django_admin_search/jquery_modal/jquery.modal.min.css
django_admin_search/static/django_admin_search/jquery_modal/jquery.modal.min.js
django_admin_search/templates/admin/custom_change_list.html
django_admin_search/templates/admin/custom_fieldset.html
django_admin_search/templates/admin/custom_search_form.html
django_admin_search/templatetags/__init__.py
django_admin_search/templatetags/advanced_search_form.py
django_admin_search-0.3.15.dist-info/LICENSE
django_admin_search-0.3.15.dist-info/METADATA
django_admin_search-0.3.15.dist-info/WHEEL
django_admin_search-0.3.15.dist-info/top_level.txt
django_admin_search-0.3.15.dist-info/RECORD
