Metadata-Version: 2.1
Name: django-admin-search
Version: 0.3.15
Summary: The "Django Admin Search" is a advanced search modal for django admin
Home-page: https://github.com/shinneider/django_admin_search
Author: Shinneider Libanio da Silva
Author-email: shinneider-libanio@hotmail.com
License: MIT
Classifier: Development Status :: 4 - Beta
Classifier: Environment :: Web Environment
Classifier: Framework :: Django
Classifier: Intended Audience :: Developers
Classifier: License :: OSI Approved :: MIT License
Classifier: Operating System :: OS Independent
Classifier: Programming Language :: Python
Classifier: Programming Language :: Python :: 3
Classifier: Programming Language :: Python :: 3.5
Classifier: Programming Language :: Python :: 3.6
Classifier: Programming Language :: Python :: 3.7
Classifier: Topic :: Internet :: WWW/HTTP
Classifier: Topic :: Software Development :: Libraries :: Python Modules
Requires-Python: >=3.3
License-File: LICENSE
Requires-Dist: django
Provides-Extra: code-quality
Requires-Dist: isort ; extra == 'code-quality'
Requires-Dist: bandit ; extra == 'code-quality'
Requires-Dist: xenon ; extra == 'code-quality'
Provides-Extra: dev
Requires-Dist: django ; extra == 'dev'
Requires-Dist: django-mock-queries ; extra == 'dev'
Requires-Dist: pylint ; extra == 'dev'
Requires-Dist: pytest-pylint ; extra == 'dev'
Requires-Dist: pytest ; extra == 'dev'
Requires-Dist: pytest-cov ; extra == 'dev'
Requires-Dist: pytest-watch ; extra == 'dev'
Requires-Dist: tox ; extra == 'dev'
Requires-Dist: six ; extra == 'dev'
